smjsindustry/__init__.py
smjsindustry/finance/__init__.py
smjsindustry/finance/build_tabText.py
smjsindustry/finance/constants.py
smjsindustry/finance/image_uri.json
smjsindustry/finance/nlp_score_type.py
smjsindustry/finance/processor.py
smjsindustry/finance/processor_config.py
smjsindustry/finance/utils.py
smjsindustry-1.0.2.dist-info/LICENSE.txt
smjsindustry-1.0.2.dist-info/METADATA
smjsindustry-1.0.2.dist-info/WHEEL
smjsindustry-1.0.2.dist-info/top_level.txt
smjsindustry-1.0.2.dist-info/RECORD
