Metadata-Version: 2.1
Name: smjsindustry
Version: 1.0.2
Summary: Open source library for industry machine learning on Amazon SageMaker.
Home-page: https://github.com/aws/sagemaker-jumpstart-industry-pack/
Author: Amazon Web Services
License: Apache License 2.0
Keywords: ML Amazon AWS AI Jumpstart Industry
Platform: UNKNOWN
Classifier: Development Status :: 5 - Production/Stable
Classifier: Intended Audience :: Developers
Classifier: Natural Language :: English
Classifier: License :: OSI Approved :: Apache Software License
Classifier: Programming Language :: Python
Classifier: Programming Language :: Python :: 3.6
Classifier: Programming Language :: Python :: 3.7
Classifier: Programming Language :: Python :: 3.8
Requires-Dist: packaging (>=20.0)
Requires-Dist: sagemaker (>=2.111.0)
Provides-Extra: all
Provides-Extra: test
Requires-Dist: tox ; extra == 'test'
Requires-Dist: flake8 ; extra == 'test'
Requires-Dist: pytest (<6.1.0) ; extra == 'test'
Requires-Dist: pytest-cov ; extra == 'test'
Requires-Dist: pytest-rerunfailures ; extra == 'test'
Requires-Dist: pytest-timeout ; extra == 'test'
Requires-Dist: pytest-xdist ; extra == 'test'
Requires-Dist: mock ; extra == 'test'
Requires-Dist: awslogs ; extra == 'test'
Requires-Dist: black ; extra == 'test'
Requires-Dist: stopit (==1.1.2) ; extra == 'test'
Requires-Dist: wheel ; extra == 'test'
